omniplot.py
omniplot/__init__.py
omniplot/_adjustText.py
omniplot/_version.py
omniplot/chipseq.py
omniplot/chipseq_utils.py
omniplot/data.py
omniplot/heatmap.py
omniplot/igraph_classes.py
omniplot/networkplot.py
omniplot/plot.py
omniplot/plot_classes.py
omniplot/proportion.py
omniplot/regressionplot.py
omniplot/scatter.py
omniplot/statistics.py
omniplot/utils.py
omniplot/cython_utils/__init__.py
omniplot/scripts/__init__.py
omniplot/scripts/gff2tss.py
omniplot-0.4.9.dist-info/LICENSE
omniplot-0.4.9.dist-info/METADATA
omniplot-0.4.9.dist-info/WHEEL
omniplot-0.4.9.dist-info/top_level.txt
omniplot-0.4.9.dist-info/RECORD
